{
  "type": "minecraft:crafting_shapeless",
  "ingredients": [
    {
      "item": "grassworld:fancyredseed"
    },
    {
      "item": "minecraft:glowstone"
    },
    {
      "item": "minecraft:glowstone"
    },
    {
      "item": "minecraft:glowstone"
    },
    {
      "item": "minecraft:glowstone"
    },
    {
      "item": "minecraft:glowstone"
    },
    {
      "item": "minecraft:glowstone"
    },
    {
      "item": "minecraft:glowstone"
    },
    {
      "item": "minecraft:glowstone"
    }
  ],
  "result": 
  {
    "item": "grassworld:glowingredseed"
  }
}